{
  "flyers-season":[
    {
      "date":"Flyers",
      "score":"PHI (1) - BOS (2)",
      "points":0,
      "totalPoints":0
    },
    {
      "date":"Devils",
      "score":"PHI (4) - NJD (6)",
      "points":0,
      "totalPoints":0
    },
    {
      "date":"Canadiens",
      "score":"PHI (3) - MTL (4) OT",
      "points":1,
      "totalPoints":1
    },
    {
      "date":"Ducks",
      "score":"PHI (3) - ANA (4) OT",
      "points":1,
      "totalPoints":2
    },
    {
      "date":"Flyers",
      "score":"PHI (6) - DAL (5)",
      "points":2,
      "totalPoints":4
    },
    {
      "date":"Flyers",
      "score":"PHI (0) - CHI (4)",
      "points":0,
      "totalPoints":4
    },
    {
      "date":"Flyers",
      "score":"PHI (5) - PIT (3)",
      "points":2,
      "totalPoints":6
    },
    {
      "date":"Red Wings",
      "score":"PHI (4) - DET (2)",
      "points":2,
      "totalPoints":8
    },
    {
      "date":"Kings",
      "score":"PHI (3) - LAK (2)",
      "points":2,
      "totalPoints":10
    },
    {
      "date":"Flyers",
      "score":"PHI (3) - TBL (4)",
      "points":0,
      "totalPoints":10
    },
    {
      "date":"Flyers",
      "score":"PHI (1) - FLA (2)",
      "points":0,
      "totalPoints":10
    },
    {
      "date":"Oilers",
      "score":"PHI (4) - EDM (1)",
      "points":2,
      "totalPoints":12
    },
    {
      "date":"Panthers",
      "score":"PHI (4) - FLA (1)",
      "points":2,
      "totalPoints":14
    },
    {
      "date":"Avalanche",
      "score":"PHI (4) - COL (3)",
      "points":2,
      "totalPoints":16
    },
    {
      "date":"Blue Jackets",
      "score":"PHI (3) - CBJ (4)",
      "points":0,
      "totalPoints":16
    },
    {
      "date":"Flyers",
      "score":"PHI (3) - MTL (6)",
      "points":0,
      "totalPoints":16
    },
    {
      "date":"Flyers",
      "score":"PHI (0) - NYR (2)",
      "points":0,
      "totalPoints":16
    },
    {
      "date":"Wild",
      "score":"PHI (2) - MIN (3)",
      "points":0,
      "totalPoints":16
    },
    {
      "date":"Blue Jackets",
      "score":"PHI (4) - CBJ (2)",
      "points":2,
      "totalPoints":18
    },
    {
      "date":"Flyers",
      "score":"PHI (0) - NYI (1) OT",
      "points":1,
      "totalPoints":19
    },
    {
      "date":"Flyers",
      "score":"PHI (2) - DET (5)",
      "points":0,
      "totalPoints":19
    },
    {
      "date":"Rangers",
      "score":"PHI (0) - NYR (3)",
      "points":0,
      "totalPoints":19
    },
    {
      "date":"Flyers",
      "score":"PHI (2) - NYR (5)",
      "points":0,
      "totalPoints":19
    },
    {
      "date":"Flyers",
      "score":"PHI (1) - SJS (2)",
      "points":0,
      "totalPoints":19
    },
    {
      "date":"Flyers",
      "score":"PHI (4) - ANA (5) OT",
      "points":1,
      "totalPoints":20
    },
    {
      "date":"Flyers",
      "score":"PHI (2) - LAK (1)",
      "points":2,
      "totalPoints":22
    },
    {
      "date":"Flyers",
      "score":"PHI (2) - CBJ (3) OT",
      "points":1,
      "totalPoints":23
    },
    {
      "date":"Devils",
      "score":"PHI (4) - NJD (1)",
      "points":2,
      "totalPoints":25
    },
    {
      "date":"Hurricanes",
      "score":"PHI (5) - CAR (1)",
      "points":2,
      "totalPoints":27
    },
    {
      "date":"Lightning",
      "score":"PHI (1) - TBL (3)",
      "points":0,
      "totalPoints":27
    },
    {
      "date":"Panthers",
      "score":"PHI (1) - FLA (2) OT",
      "points":1,
      "totalPoints":28
    },
    {
      "date":"Flyers",
      "score":"PHI (7) - TOR (4)",
      "points":2,
      "totalPoints":30
    },
    {
      "date":"Flyers",
      "score":"PHI (4) - WPG (3)",
      "points":2,
      "totalPoints":32
    },
    {
      "date":"Flyers",
      "score":"PHI (5) - MIN (2)",
      "points":2,
      "totalPoints":34
    },
    {
      "date":"Flyers",
      "score":"PHI (1) - NSH (4)",
      "points":0,
      "totalPoints":34
    },
    {
      "date":"Flyers",
      "score":"PHI (2) - ARI (4)",
      "points":0,
      "totalPoints":34
    },
    {
      "date":"Flyers",
      "score":"PHI (3) - COL (4) OT",
      "points":1,
      "totalPoints":35
    },
    {
      "date":"Flyers",
      "score":"PHI (1) - CAR (2)",
      "points":0,
      "totalPoints":35
    },
    {
      "date":"Flyers",
      "score":"PHI (2) - NJD (5)",
      "points":0,
      "totalPoints":35
    },
    {
      "date":"Senators",
      "score":"PHI (2) - OTT (1)",
      "points":2,
      "totalPoints":37
    },
    {
      "date":"Capitals",
      "score":"PHI (3) - WSH (2)",
      "points":2,
      "totalPoints":39
    },
    {
      "date":"Bruins",
      "score":"PHI (1) - BOS (3)",
      "points":0,
      "totalPoints":39
    },
    {
      "date":"Lightning",
      "score":"PHI (7) - TBL (3)",
      "points":2,
      "totalPoints":41
    },
    {
      "date":"Flyers",
      "score":"PHI (0) - WSH (1)",
      "points":0,
      "totalPoints":41
    },
    {
      "date":"Canucks",
      "score":"PHI (0) - VAN (4)",
      "points":0,
      "totalPoints":41
    },
    {
      "date":"Flyers",
      "score":"PHI (4) - BUF (3)",
      "points":2,
      "totalPoints":43
    },
    {
      "date":"Flyers",
      "score":"PHI (4) - NYI (7)",
      "points":0,
      "totalPoints":43
    },
    {
      "date":"Penguins",
      "score":"PHI (3) - PIT (2)",
      "points":2,
      "totalPoints":45
    },
    {
      "date":"Coyotes",
      "score":"PHI (4) - ARI (3)",
      "points":2,
      "totalPoints":47
    },
    {
      "date":"Jets",
      "score":"PHI (5) - WPG (2)",
      "points":2,
      "totalPoints":49
    },
    {
      "date":"Maple Leafs",
      "score":"PHI (1) - TOR (0)",
      "points":2,
      "totalPoints":51
    },
    {
      "date":"Islanders",
      "score":"PHI (2) - NYI (3) OT",
      "points":1,
      "totalPoints":52
    },
    {
      "date":"Flyers",
      "score":"PHI (3) - WSH (1)",
      "points":2,
      "totalPoints":54
    },
    {
      "date":"Flyers",
      "score":"PHI (1) - MTL (2) OT",
      "points":1,
      "totalPoints":55
    },
    {
      "date":"Flyers",
      "score":"PHI (3) - CBJ (4) OT",
      "points":1,
      "totalPoints":56
    },
    {
      "date":"Flyers",
      "score":"PHI (2) - BUF (1)",
      "points":2,
      "totalPoints":58
    },
    {
      "date":"Blue Jackets",
      "score":"PHI (2) - CBJ (5)",
      "points":0,
      "totalPoints":58
    },
    {
      "date":"Sabres",
      "score":"PHI (2) - BUF (3) OT",
      "points":1,
      "totalPoints":59
    },
    {
      "date":"Predators",
      "score":"PHI (3) - NSH (2)",
      "points":2,
      "totalPoints":61
    },
    {
      "date":"Capitals",
      "score":"PHI (3) - WSH (2)",
      "points":2,
      "totalPoints":63
    },
    {
      "date":"Flyers",
      "score":"PHI (1) - CAR (4)",
      "points":0,
      "totalPoints":63
    },
    {
      "date":"Flyers",
      "score":"PHI (2) - TOR (3)",
      "points":0,
      "totalPoints":63
    },
    {
      "date":"Rangers",
      "score":"PHI (4) - NYR (2)",
      "points":2,
      "totalPoints":65
    },
    {
      "date":"Flames",
      "score":"PHI (2) - CGY (3) OT",
      "points":1,
      "totalPoints":66
    },
    {
      "date":"Blues",
      "score":"PHI (3) - STL (1)",
      "points":2,
      "totalPoints":68
    },
    {
      "date":"Flyers",
      "score":"PHI (2) - BOS (3) OT",
      "points":1,
      "totalPoints":69
    },
    {
      "date":"Flyers",
      "score":"PHI (2) - NJD (5)",
      "points":0,
      "totalPoints":69
    },
    {
      "date":"Stars",
      "score":"PHI (1) - DAL (2)",
      "points":0,
      "totalPoints":69
    },
    {
      "date":"Flyers",
      "score":"PHI (0) - STL (1) OT",
      "points":1,
      "totalPoints":70
    },
    {
      "date":"Red Wings",
      "score":"PHI (7) - DET (2)",
      "points":2,
      "totalPoints":72
    },
    {
      "date":"Flyers",
      "score":"PHI (1) - OTT (2) OT",
      "points":1,
      "totalPoints":73
    },
    {
      "date":"Flyers",
      "score":"PHI (1) - VAN (4)",
      "points":0,
      "totalPoints":73
    },
    {
      "date":"Flyers",
      "score":"PHI (1) - CGY (4)",
      "points":0,
      "totalPoints":73
    },
    {
      "date":"Flyers",
      "score":"PHI (4) - EDM (5) OT",
      "points":1,
      "totalPoints":74
    },
    {
      "date":"Blackhawks",
      "score":"PHI (4) - CHI (1)",
      "points":2,
      "totalPoints":76
    },
    {
      "date":"Sharks",
      "score":"PHI (2) - SJS (3) OT",
      "points":1,
      "totalPoints":77
    },
    {
      "date":"Flyers",
      "score":"PHI (4) - PIT (1)",
      "points":2,
      "totalPoints":79
    },
    {
      "date":"Flyers",
      "score":"PHI (2) - CAR (3) OT",
      "points":1,
      "totalPoints":80
    },
    {
      "date":"Penguins",
      "score":"PHI (4) - PIT (1)",
      "points":2,
      "totalPoints":82
    },
    {
      "date":"Islanders",
      "score":"PHI (5) - NYI (4)",
      "points":2,
      "totalPoints":84
    },
    {
      "date":"Hurricanes",
      "score":"PHI (1) - CAR (3)",
      "points":0,
      "totalPoints":84
    },
    {
      "date":"Senators",
      "score":"PHI (1) - OTT (3)",
      "points":0,
      "totalPoints":84
    }
  ]
}